deliciousbytes/__init__.py
deliciousbytes/version.txt
deliciousbytes/utilities/__init__.py
deliciousbytes-1.1.1.dist-info/licenses/LICENSE.md
deliciousbytes-1.1.1.dist-info/METADATA
deliciousbytes-1.1.1.dist-info/WHEEL
deliciousbytes-1.1.1.dist-info/top_level.txt
deliciousbytes-1.1.1.dist-info/zip-safe
deliciousbytes-1.1.1.dist-info/RECORD
