Metadata-Version: 2.4
Name: deliciousbytes
Version: 1.1.1
Summary: Streamlined binary data type encoding and decoding for Python.
Author: Daniel Sissman
License-Expression: MIT
Project-URL: documentation, https://github.com/bluebinary/deliciousbytes/blob/main/README.md
Project-URL: changelog, https://github.com/bluebinary/deliciousbytes/blob/main/CHANGELOG.md
Project-URL: repository, https://github.com/bluebinary/deliciousbytes
Project-URL: issues, https://github.com/bluebinary/deliciousbytes/issues
Project-URL: homepage, https://github.com/bluebinary/deliciousbytes
Keywords: bytes,encoding,decoding,data types
Platform: any
Classifier: Programming Language :: Python :: 3
Classifier: Programming Language :: Python :: 3.10
Classifier: Programming Language :: Python :: 3.11
Classifier: Programming Language :: Python :: 3.12
Classifier: Programming Language :: Python :: 3.13
Requires-Python: >=3.10
License-File: LICENSE.md
Requires-Dist: enumerific>=1.0.1
Requires-Dist: classicist>=1.0.0
Provides-Extra: development
Requires-Dist: black==24.10.*; extra == "development"
Requires-Dist: pytest==8.3.*; extra == "development"
Requires-Dist: pytest-codeblocks; extra == "development"
Provides-Extra: distribution
Requires-Dist: build; extra == "distribution"
Requires-Dist: twine; extra == "distribution"
Requires-Dist: wheel; extra == "distribution"
Dynamic: license-file
